yangcore/LICENSE
yangcore/__init__.py
yangcore/__main__.py
yangcore/dal.py
yangcore/db_utils.py
yangcore/demo_app.py
yangcore/handler.py
yangcore/native.py
yangcore/rcsvr.py
yangcore/utils.py
yangcore/val.py
yangcore/yangcore.py
yangcore/yl.py
yangcore/plugins/README
yangcore-0.0.67.dist-info/METADATA
yangcore-0.0.67.dist-info/NOTICE
yangcore-0.0.67.dist-info/WHEEL
yangcore-0.0.67.dist-info/entry_points.txt
yangcore-0.0.67.dist-info/top_level.txt
yangcore-0.0.67.dist-info/RECORD
