Metadata-Version: 2.2
Name: yangcore
Version: 0.0.67
Summary: YANGcore (a RESTCONF-based Application Server)
Home-page: https://watsen.net/products/yangcore
Author: Watsen Networks
Author-email: info@watsen.net
License: Non Production Use License
Project-URL: Documentation, https://watsen.net/docs/yangcore
Project-URL: License, https://watsen.net/sales/non-production-use.html
Keywords: ietf,rfc,7950,yang,8040,restconf
Classifier: Development Status :: 2 - Pre-Alpha
Classifier: Environment :: Console
Classifier: Intended Audience :: Information Technology
Classifier: Intended Audience :: System Administrators
Classifier: Intended Audience :: Telecommunications Industry
Classifier: License :: Other/Proprietary License
Classifier: Natural Language :: English
Classifier: Operating System :: MacOS
Classifier: Operating System :: POSIX :: Linux
Classifier: Programming Language :: Python :: 3.11
Classifier: Programming Language :: Python :: 3.12
Classifier: Topic :: Communications
Classifier: Topic :: Internet
Classifier: Topic :: Security
Requires-Python: <3.13,>=3.11
License-File: NOTICE
Requires-Dist: aiohttp<4.0.0
Requires-Dist: basicauth
Requires-Dist: cryptography>3.1
Requires-Dist: fifolock
Requires-Dist: passlib
Requires-Dist: pem
Requires-Dist: pyasn1
Requires-Dist: pyasn1-modules>=0.2.6
Requires-Dist: pysqlite3
Requires-Dist: pymysql
Requires-Dist: sqlalchemy<2.0.0
Requires-Dist: yangson>=1.4.15
